[
    {
        "id": "flow_outbound",
        "type": "tab",
        "label": "Outbound Module",
        "disabled": false,
        "info": "Complete outbound module backend with proper data relationships"
    },
    {
        "id": "broker_emqx",
        "type": "mqtt-broker",
        "name": "EMQX Broker",
        "broker": "emqx",
        "port": "1883",
        "clientid": "",
        "autoConnect": true,
        "usetls": false,
        "protocolVersion": "4",
        "keepalive": "60",
        "cleansession": true,
        "autoUnsubscribe": true,
        "birthTopic": "",
        "birthQos": "0",
        "birthRetain": "false",
        "birthPayload": "",
        "birthMsg": {},
        "closeTopic": "",
        "closeQos": "0",
        "closeRetain": "false",
        "closePayload": "",
        "closeMsg": {},
        "willTopic": "",
        "willQos": "0",
        "willRetain": "false",
        "willPayload": "",
        "willMsg": {},
        "userProps": "",
        "sessionExpiry": ""
    },
    {
        "id": "group_mock_generators",
        "type": "group",
        "z": "flow_outbound",
        "name": "1. Mock Data Generators",
        "style": {
            "fill": "#ffeb3b",
            "fill-opacity": "0.3",
            "label": true,
            "stroke": "#f9a825"
        },
        "nodes": [
            "inject_dn", "func_gen_dn",
            "inject_wave", "func_gen_wave",
            "inject_picking", "func_gen_picking",
            "inject_staging", "func_gen_staging",
            "inject_docks", "func_gen_docks",
            "inject_reset", "func_reset",
            "mqtt_out_state", "debug_mock"
        ],
        "x": 34,
        "y": 19,
        "w": 692,
        "h": 422
    },
    {
        "id": "inject_dn",
        "type": "inject",
        "z": "flow_outbound",
        "g": "group_mock_generators",
        "name": "🔄 Generate DNs",
        "props": [{"p": "topic", "vt": "str"}],
        "repeat": "",
        "crontab": "",
        "once": false,
        "onceDelay": 0.1,
        "topic": "Henkelv2/Shanghai/Logistics/Costing/State/DN_Workflow_DB",
        "x": 130,
        "y": 80,
        "wires": [["func_gen_dn"]]
    },
    {
        "id": "func_gen_dn",
        "type": "function",
        "z": "flow_outbound",
        "g": "group_mock_generators",
        "name": "Generate 3-5 Orders",
        "func": "const TOPIC = msg.topic;\nconst statuses = ['NEW', 'RELEASED', 'RELEASED', 'RELEASED']; // More RELEASED for wave testing\nconst customers = ['CUSTOMER-A', 'CUSTOMER-B', 'HENKEL-SUZHOU', 'HENKEL-BEIJING'];\nconst materials = ['GLUE-500', 'SEALANT-X', 'ADHESIVE-PRO', 'COATING-UV'];\n\nlet dnDB = global.get('outbound_dn_db') || { items: [] };\n\n// Generate 3-5 new orders\nlet count = Math.floor(Math.random() * 3) + 3;\nfor (let i = 0; i < count; i++) {\n    let status = statuses[Math.floor(Math.random() * statuses.length)];\n    let dnNo = 'DN-' + new Date().toISOString().slice(0,10).replace(/-/g,'') + '-' + String(dnDB.items.length + 1).padStart(3, '0');\n    \n    let order = {\n        dn_no: dnNo,\n        id: dnNo,\n        type: Math.random() > 0.3 ? 'SALES_ORDER' : 'TRANSFER_OUT',\n        status: status,\n        customer: customers[Math.floor(Math.random() * customers.length)],\n        destination: 'Shanghai-' + (Math.floor(Math.random() * 3) + 1),\n        warehouse: 'WH-SHANGHAI',\n        requested_date: new Date(Date.now() + 86400000 * Math.floor(Math.random() * 7)).toISOString().split('T')[0],\n        wave_id: null,\n        lines: [\n            { code: materials[Math.floor(Math.random() * materials.length)], qty: Math.floor(Math.random() * 100) + 10, qty_allocated: 0 },\n            { code: materials[Math.floor(Math.random() * materials.length)], qty: Math.floor(Math.random() * 50) + 5, qty_allocated: 0 }\n        ],\n        created_at: Date.now(),\n        priority: Math.random() > 0.7 ? 'HIGH' : 'NORMAL'\n    };\n    dnDB.items.unshift(order);\n}\n\n// Keep only last 30\nif (dnDB.items.length > 30) dnDB.items = dnDB.items.slice(0, 30);\nglobal.set('outbound_dn_db', dnDB);\n\nmsg.payload = {\n    version: '1.0',\n    topics: [{ path: TOPIC, type: 'state', value: dnDB }]\n};\n\nnode.warn('Generated ' + count + ' orders. Total: ' + dnDB.items.length);\nreturn msg;",
        "outputs": 1,
        "timeout": "",
        "noerr": 0,
        "initialize": "",
        "finalize": "",
        "libs": [],
        "x": 350,
        "y": 80,
        "wires": [["mqtt_out_state", "debug_mock"]]
    },
    {
        "id": "inject_wave",
        "type": "inject",
        "z": "flow_outbound",
        "g": "group_mock_generators",
        "name": "🔄 Generate Wave (with DNs)",
        "props": [{"p": "topic", "vt": "str"}],
        "repeat": "",
        "crontab": "",
        "once": false,
        "onceDelay": 0.1,
        "topic": "Henkelv2/Shanghai/Logistics/Outbound/State/Wave_List",
        "x": 170,
        "y": 140,
        "wires": [["func_gen_wave"]]
    },
    {
        "id": "func_gen_wave",
        "type": "function",
        "z": "flow_outbound",
        "g": "group_mock_generators",
        "name": "Generate Wave + Link DNs",
        "func": "const TOPIC_WAVE = msg.topic;\nconst TOPIC_DN = 'Henkelv2/Shanghai/Logistics/Costing/State/DN_Workflow_DB';\nconst carriers = ['SF-EXPRESS', 'DHL', 'SINOTRANS', 'JD-LOGISTICS'];\nconst routes = ['Shanghai North', 'Shanghai South', 'Suzhou Route', 'Hangzhou Line'];\n\nlet waveDB = global.get('wave_db') || { items: [] };\nlet dnDB = global.get('outbound_dn_db') || { items: [] };\n\n// Find RELEASED DNs without wave assignment\nlet availableDNs = dnDB.items.filter(o => \n    o.status === 'RELEASED' && !o.wave_id\n);\n\nif (availableDNs.length === 0) {\n    node.warn('No RELEASED DNs available. Generate DNs first!');\n    return null;\n}\n\n// Generate wave ID\nlet datePart = new Date().toISOString().slice(0, 10).replace(/-/g, '');\nlet key = 'wave_seq_' + datePart;\nlet seq = (global.get(key) || 0) + 1;\nglobal.set(key, seq);\n\n// Pick 2-4 DNs for this wave\nlet pickCount = Math.min(Math.floor(Math.random() * 3) + 2, availableDNs.length);\nlet selectedDNs = availableDNs.slice(0, pickCount);\n\n// Calculate line count from selected DNs\nlet lineCount = selectedDNs.reduce((sum, dn) => sum + (dn.lines || []).length, 0);\n\n// Create wave with REAL delivery_ids\nlet wave = {\n    wave_id: 'WAVE-' + datePart + '-' + String(seq).padStart(3, '0'),\n    status: 'PLANNED',\n    ship_date: new Date(Date.now() + 86400000 * Math.floor(Math.random() * 3)).toISOString().split('T')[0],\n    carrier: carriers[Math.floor(Math.random() * carriers.length)],\n    route: routes[Math.floor(Math.random() * routes.length)],\n    pick_method: Math.random() > 0.5 ? 'BATCH' : 'DISCRETE',\n    delivery_ids: selectedDNs.map(d => d.dn_no),\n    delivery_count: selectedDNs.length,\n    line_count: lineCount,\n    picks_completed: 0,\n    picks_total: 0,\n    created_at: Date.now()\n};\n\n// Update DN status to WAVE_ASSIGNED\nselectedDNs.forEach(dn => {\n    dn.wave_id = wave.wave_id;\n    dn.status = 'WAVE_ASSIGNED';\n});\n\nwaveDB.items.unshift(wave);\n\n// Keep only last 20 waves\nif (waveDB.items.length > 20) waveDB.items = waveDB.items.slice(0, 20);\n\nglobal.set('wave_db', waveDB);\nglobal.set('outbound_dn_db', dnDB);\n\nnode.warn('Created wave ' + wave.wave_id + ' with ' + selectedDNs.length + ' orders: ' + wave.delivery_ids.join(', '));\n\n// Return both wave and DN updates\nlet msgWave = {\n    topic: TOPIC_WAVE,\n    payload: { version: '1.0', topics: [{ path: TOPIC_WAVE, type: 'state', value: waveDB }] }\n};\nlet msgDN = {\n    topic: TOPIC_DN,\n    payload: { version: '1.0', topics: [{ path: TOPIC_DN, type: 'state', value: dnDB }] }\n};\n\nreturn [[msgWave, msgDN]];",
        "outputs": 1,
        "timeout": "",
        "noerr": 0,
        "initialize": "",
        "finalize": "",
        "libs": [],
        "x": 370,
        "y": 140,
        "wires": [["mqtt_out_state", "debug_mock"]]
    },
    {
        "id": "inject_picking",
        "type": "inject",
        "z": "flow_outbound",
        "g": "group_mock_generators",
        "name": "🔄 Generate Pick Tasks",
        "props": [{"p": "topic", "vt": "str"}],
        "repeat": "",
        "crontab": "",
        "once": false,
        "onceDelay": 0.1,
        "topic": "Henkelv2/Shanghai/Logistics/Outbound/State/Picking_Queue",
        "x": 150,
        "y": 200,
        "wires": [["func_gen_picking"]]
    },
    {
        "id": "func_gen_picking",
        "type": "function",
        "z": "flow_outbound",
        "g": "group_mock_generators",
        "name": "Generate Tasks from DNs",
        "func": "const TOPIC = msg.topic;\nconst locations = ['A-01-01', 'A-02-03', 'B-01-02', 'B-03-01', 'C-02-04'];\n\nlet dnDB = global.get('outbound_dn_db') || { items: [] };\nlet waveDB = global.get('wave_db') || { items: [] };\nlet taskDB = global.get('outbound_task_db') || { items: [] };\n\n// Find DNs that are ALLOCATED or IN_PROGRESS waves\nlet allocatedDNs = dnDB.items.filter(o => \n    o.status === 'ALLOCATED' || o.status === 'PICKING'\n);\n\nif (allocatedDNs.length === 0) {\n    // Fallback: create sample tasks\n    let count = Math.floor(Math.random() * 5) + 3;\n    for (let i = 0; i < count; i++) {\n        taskDB.items.unshift({\n            task_id: 'PICK-' + Date.now() + '-' + i,\n            status: 'PENDING',\n            material_code: ['GLUE-500', 'SEALANT-X', 'ADHESIVE-PRO'][Math.floor(Math.random() * 3)],\n            material_name: 'Material ' + (i + 1),\n            batch: 'B2026' + String(Math.floor(Math.random() * 1000)).padStart(3, '0'),\n            from_location: locations[Math.floor(Math.random() * locations.length)],\n            to_location: 'STAGE-0' + (Math.floor(Math.random() * 3) + 1),\n            qty: Math.floor(Math.random() * 50) + 10,\n            uom: 'EA',\n            wave_id: 'WAVE-SAMPLE',\n            dn_no: 'DN-SAMPLE-' + i,\n            priority: Math.random() > 0.7 ? 'HIGH' : 'NORMAL',\n            created_at: Date.now()\n        });\n    }\n} else {\n    // Create tasks from real allocated DNs\n    allocatedDNs.forEach(dn => {\n        (dn.lines || []).forEach((line, idx) => {\n            // Check if task already exists\n            let existingTask = taskDB.items.find(t => t.dn_no === dn.dn_no && t.material_code === line.code);\n            if (!existingTask) {\n                taskDB.items.unshift({\n                    task_id: 'PICK-' + Date.now() + '-' + Math.floor(Math.random() * 1000),\n                    status: 'PENDING',\n                    material_code: line.code,\n                    material_name: line.code,\n                    batch: 'B2026' + String(Math.floor(Math.random() * 1000)).padStart(3, '0'),\n                    from_location: locations[Math.floor(Math.random() * locations.length)],\n                    to_location: 'STAGE-01',\n                    qty: line.qty,\n                    uom: 'EA',\n                    wave_id: dn.wave_id || 'NO-WAVE',\n                    dn_no: dn.dn_no,\n                    priority: dn.priority || 'NORMAL',\n                    created_at: Date.now()\n                });\n            }\n        });\n        dn.status = 'PICKING';\n    });\n    global.set('outbound_dn_db', dnDB);\n}\n\nif (taskDB.items.length > 50) taskDB.items = taskDB.items.slice(0, 50);\nglobal.set('outbound_task_db', taskDB);\n\nmsg.payload = {\n    version: '1.0',\n    topics: [{ path: TOPIC, type: 'state', value: { tasks: taskDB.items } }]\n};\n\nnode.warn('Generated ' + taskDB.items.length + ' pick tasks');\nreturn msg;",
        "outputs": 1,
        "timeout": "",
        "noerr": 0,
        "initialize": "",
        "finalize": "",
        "libs": [],
        "x": 370,
        "y": 200,
        "wires": [["mqtt_out_state", "debug_mock"]]
    },
    {
        "id": "inject_staging",
        "type": "inject",
        "z": "flow_outbound",
        "g": "group_mock_generators",
        "name": "🔄 Generate Staging",
        "props": [{"p": "topic", "vt": "str"}],
        "repeat": "",
        "crontab": "",
        "once": false,
        "onceDelay": 0.1,
        "topic": "Henkelv2/Shanghai/Logistics/Outbound/State/Staging_Area",
        "x": 140,
        "y": 260,
        "wires": [["func_gen_staging"]]
    },
    {
        "id": "func_gen_staging",
        "type": "function",
        "z": "flow_outbound",
        "g": "group_mock_generators",
        "name": "Generate Staging Areas",
        "func": "const TOPIC = msg.topic;\nconst areas = ['STAGE-01', 'STAGE-02', 'STAGE-03', 'STAGE-04'];\nconst materials = ['GLUE-500', 'SEALANT-X', 'ADHESIVE-PRO'];\n\nlet stagingAreas = areas.map(areaId => {\n    let itemCount = Math.floor(Math.random() * 4);\n    let items = [];\n    for (let i = 0; i < itemCount; i++) {\n        items.push({\n            hu_id: 'HU-' + Math.floor(Math.random() * 10000),\n            material_code: materials[Math.floor(Math.random() * materials.length)],\n            qty: Math.floor(Math.random() * 100) + 10,\n            dn_no: 'DN-' + Math.floor(Math.random() * 10000),\n            wave_id: 'WAVE-' + Math.floor(Math.random() * 100),\n            staged_at: Date.now() - Math.floor(Math.random() * 3600000)\n        });\n    }\n    return {\n        area_id: areaId,\n        capacity: 20,\n        used: items.length,\n        items: items\n    };\n});\n\nglobal.set('staging_areas', { areas: stagingAreas });\n\nmsg.payload = {\n    version: '1.0',\n    topics: [{ path: TOPIC, type: 'state', value: { areas: stagingAreas } }]\n};\n\nreturn msg;",
        "outputs": 1,
        "timeout": "",
        "noerr": 0,
        "initialize": "",
        "finalize": "",
        "libs": [],
        "x": 370,
        "y": 260,
        "wires": [["mqtt_out_state", "debug_mock"]]
    },
    {
        "id": "inject_docks",
        "type": "inject",
        "z": "flow_outbound",
        "g": "group_mock_generators",
        "name": "🔄 Generate Docks",
        "props": [{"p": "topic", "vt": "str"}],
        "repeat": "",
        "crontab": "",
        "once": false,
        "onceDelay": 0.1,
        "topic": "Henkelv2/Shanghai/Logistics/Outbound/State/Loading_Docks",
        "x": 140,
        "y": 320,
        "wires": [["func_gen_docks"]]
    },
    {
        "id": "func_gen_docks",
        "type": "function",
        "z": "flow_outbound",
        "g": "group_mock_generators",
        "name": "Generate Loading Docks",
        "func": "const TOPIC = msg.topic;\nconst dockStatuses = ['AVAILABLE', 'WAITING', 'LOADING', 'COMPLETED'];\nconst carriers = ['SF-EXPRESS', 'DHL', 'SINOTRANS', 'JD-LOGISTICS'];\n\nlet docks = [];\nfor (let i = 1; i <= 6; i++) {\n    let status = dockStatuses[Math.floor(Math.random() * dockStatuses.length)];\n    docks.push({\n        dock_id: 'DOCK-0' + i,\n        status: status,\n        carrier: status !== 'AVAILABLE' ? carriers[Math.floor(Math.random() * carriers.length)] : null,\n        vehicle: status !== 'AVAILABLE' ? '沪A' + String(Math.floor(Math.random() * 90000) + 10000) : null,\n        shipments: status === 'LOADING' || status === 'WAITING' ? Math.floor(Math.random() * 3) + 1 : 0,\n        total_items: status === 'LOADING' ? Math.floor(Math.random() * 50) + 10 : 0,\n        loaded_items: status === 'LOADING' ? Math.floor(Math.random() * 30) : 0,\n        arrival_time: status !== 'AVAILABLE' ? Date.now() - Math.floor(Math.random() * 7200000) : null\n    });\n}\n\nglobal.set('loading_docks', { docks: docks });\n\nmsg.payload = {\n    version: '1.0',\n    topics: [{ path: TOPIC, type: 'state', value: { docks: docks } }]\n};\n\nreturn msg;",
        "outputs": 1,
        "timeout": "",
        "noerr": 0,
        "initialize": "",
        "finalize": "",
        "libs": [],
        "x": 370,
        "y": 320,
        "wires": [["mqtt_out_state", "debug_mock"]]
    },
    {
        "id": "inject_reset",
        "type": "inject",
        "z": "flow_outbound",
        "g": "group_mock_generators",
        "name": "🗑️ RESET ALL DATA",
        "props": [],
        "repeat": "",
        "crontab": "",
        "once": false,
        "onceDelay": 0.1,
        "x": 140,
        "y": 380,
        "wires": [["func_reset"]]
    },
    {
        "id": "func_reset",
        "type": "function",
        "z": "flow_outbound",
        "g": "group_mock_generators",
        "name": "Clear All Data",
        "func": "// Clear all global context\nglobal.set('outbound_dn_db', { items: [] });\nglobal.set('wave_db', { items: [] });\nglobal.set('outbound_task_db', { items: [] });\nglobal.set('shipment_list', { items: [] });\nglobal.set('staging_areas', { areas: [] });\nglobal.set('loading_docks', { docks: [] });\n\n// Reset sequence counters\nlet today = new Date().toISOString().slice(0, 10).replace(/-/g, '');\nglobal.set('wave_seq_' + today, 0);\n\nnode.warn('All outbound data cleared!');\n\n// Publish empty states\nlet topics = [\n    'Henkelv2/Shanghai/Logistics/Costing/State/DN_Workflow_DB',\n    'Henkelv2/Shanghai/Logistics/Outbound/State/Wave_List',\n    'Henkelv2/Shanghai/Logistics/Outbound/State/Picking_Queue',\n    'Henkelv2/Shanghai/Logistics/Outbound/State/Staging_Area',\n    'Henkelv2/Shanghai/Logistics/Outbound/State/Loading_Docks',\n    'Henkelv2/Shanghai/Logistics/Outbound/State/Shipment_List'\n];\n\nlet messages = topics.map(t => ({\n    topic: t,\n    payload: { version: '1.0', topics: [{ path: t, type: 'state', value: { items: [] } }] }\n}));\n\nreturn [messages];",
        "outputs": 1,
        "timeout": "",
        "noerr": 0,
        "initialize": "",
        "finalize": "",
        "libs": [],
        "x": 350,
        "y": 380,
        "wires": [["mqtt_out_state"]]
    },
    {
        "id": "mqtt_out_state",
        "type": "mqtt out",
        "z": "flow_outbound",
        "g": "group_mock_generators",
        "name": "Publish State",
        "topic": "",
        "qos": "0",
        "retain": "true",
        "broker": "broker_emqx",
        "x": 590,
        "y": 200,
        "wires": []
    },
    {
        "id": "debug_mock",
        "type": "debug",
        "z": "flow_outbound",
        "g": "group_mock_generators",
        "name": "View Mock Data",
        "active": true,
        "tosidebar": true,
        "console": false,
        "tostatus": false,
        "complete": "payload",
        "targetType": "msg",
        "x": 600,
        "y": 300,
        "wires": []
    },
    {
        "id": "group_order_actions",
        "type": "group",
        "z": "flow_outbound",
        "name": "2. Order Actions",
        "style": {
            "fill": "#a3e635",
            "fill-opacity": "0.3",
            "label": true,
            "stroke": "#65a30d"
        },
        "nodes": [
            "mqtt_in_create_order", "func_create_order",
            "mqtt_in_hold", "func_hold",
            "mqtt_in_release_hold", "func_release_hold",
            "mqtt_in_review", "func_review",
            "mqtt_out_dn_state"
        ],
        "x": 754,
        "y": 19,
        "w": 572,
        "h": 302
    },
    {
        "id": "mqtt_in_create_order",
        "type": "mqtt in",
        "z": "flow_outbound",
        "g": "group_order_actions",
        "name": "Action: Create_Order",
        "topic": "Henkelv2/Shanghai/Logistics/Outbound/Action/Create_Order",
        "qos": "0",
        "datatype": "json",
        "broker": "broker_emqx",
        "x": 870,
        "y": 80,
        "wires": [["func_create_order"]]
    },
    {
        "id": "func_create_order",
        "type": "function",
        "z": "flow_outbound",
        "g": "group_order_actions",
        "name": "Create Order",
        "func": "const TOPIC = 'Henkelv2/Shanghai/Logistics/Costing/State/DN_Workflow_DB';\nlet action = msg.payload;\n\nlet dnDB = global.get('outbound_dn_db') || { items: [] };\n\n// Generate DN number\nlet datePart = new Date().toISOString().slice(0,10).replace(/-/g,'');\nlet dnNo = 'DN-' + datePart + '-' + String(dnDB.items.length + 1).padStart(3, '0');\n\nlet newOrder = {\n    dn_no: dnNo,\n    id: dnNo,\n    type: action.type || 'SALES_ORDER',\n    status: 'NEW',\n    customer: action.customer || action.destination || 'Unknown',\n    destination: action.destination || action.customer || 'Unknown',\n    warehouse: action.warehouse || 'WH-SHANGHAI',\n    requested_date: action.requestedDate || new Date().toISOString().split('T')[0],\n    wave_id: null,\n    lines: (action.lines || []).map(l => ({\n        code: l.code,\n        qty: l.qty,\n        qty_allocated: 0\n    })),\n    created_at: Date.now(),\n    created_by: action.operator || 'System',\n    priority: 'NORMAL'\n};\n\ndnDB.items.unshift(newOrder);\nglobal.set('outbound_dn_db', dnDB);\n\nmsg.topic = TOPIC;\nmsg.payload = {\n    version: '1.0',\n    topics: [{ path: TOPIC, type: 'state', value: dnDB }]\n};\n\nnode.warn('Created order: ' + dnNo);\nreturn msg;",
        "outputs": 1,
        "timeout": "",
        "noerr": 0,
        "initialize": "",
        "finalize": "",
        "libs": [],
        "x": 1070,
        "y": 80,
        "wires": [["mqtt_out_dn_state"]]
    },
    {
        "id": "mqtt_in_hold",
        "type": "mqtt in",
        "z": "flow_outbound",
        "g": "group_order_actions",
        "name": "Action: Hold_Order",
        "topic": "Henkelv2/Shanghai/Logistics/Outbound/Action/Hold_Order",
        "qos": "0",
        "datatype": "json",
        "broker": "broker_emqx",
        "x": 860,
        "y": 140,
        "wires": [["func_hold"]]
    },
    {
        "id": "func_hold",
        "type": "function",
        "z": "flow_outbound",
        "g": "group_order_actions",
        "name": "Hold Order",
        "func": "const TOPIC = 'Henkelv2/Shanghai/Logistics/Costing/State/DN_Workflow_DB';\nlet action = msg.payload;\n\nlet dnDB = global.get('outbound_dn_db') || { items: [] };\nlet order = dnDB.items.find(o => o.dn_no === action.dn_no || o.id === action.dn_no);\n\nif (!order) {\n    node.warn('Hold Error: Order not found ' + action.dn_no);\n    return null;\n}\n\n// Can only hold orders not yet in execution\nconst canHold = ['NEW', 'RELEASED', 'WAVE_ASSIGNED', 'APPROVED'].includes(order.status);\nif (!canHold) {\n    node.warn('Hold Error: Cannot hold order in status ' + order.status);\n    return null;\n}\n\n// Store previous status and hold\norder.previous_status = order.status;\norder.status = 'ON_HOLD';\norder.hold_reason = action.reason || 'Manual hold';\norder.hold_at = Date.now();\norder.hold_by = action.operator || 'System';\n\n// If in a wave, remove from wave\nif (order.wave_id) {\n    let waveDB = global.get('wave_db') || { items: [] };\n    let wave = waveDB.items.find(w => w.wave_id === order.wave_id);\n    if (wave && wave.status === 'PLANNED') {\n        wave.delivery_ids = wave.delivery_ids.filter(id => id !== order.dn_no);\n        wave.delivery_count = wave.delivery_ids.length;\n        global.set('wave_db', waveDB);\n    }\n    order.previous_wave_id = order.wave_id;\n    order.wave_id = null;\n}\n\nglobal.set('outbound_dn_db', dnDB);\n\nmsg.topic = TOPIC;\nmsg.payload = {\n    version: '1.0',\n    topics: [{ path: TOPIC, type: 'state', value: dnDB }]\n};\n\nnode.warn('Order ' + action.dn_no + ' put on hold');\nreturn msg;",
        "outputs": 1,
        "timeout": "",
        "noerr": 0,
        "initialize": "",
        "finalize": "",
        "libs": [],
        "x": 1060,
        "y": 140,
        "wires": [["mqtt_out_dn_state"]]
    },
    {
        "id": "mqtt_in_release_hold",
        "type": "mqtt in",
        "z": "flow_outbound",
        "g": "group_order_actions",
        "name": "Action: Release_Hold",
        "topic": "Henkelv2/Shanghai/Logistics/Outbound/Action/Release_Hold",
        "qos": "0",
        "datatype": "json",
        "broker": "broker_emqx",
        "x": 870,
        "y": 200,
        "wires": [["func_release_hold"]]
    },
    {
        "id": "func_release_hold",
        "type": "function",
        "z": "flow_outbound",
        "g": "group_order_actions",
        "name": "Release Hold",
        "func": "const TOPIC = 'Henkelv2/Shanghai/Logistics/Costing/State/DN_Workflow_DB';\nlet action = msg.payload;\n\nlet dnDB = global.get('outbound_dn_db') || { items: [] };\nlet order = dnDB.items.find(o => o.dn_no === action.dn_no || o.id === action.dn_no);\n\nif (!order) {\n    node.warn('Release Hold Error: Order not found');\n    return null;\n}\n\nif (order.status !== 'ON_HOLD') {\n    node.warn('Release Hold Error: Order not on hold');\n    return null;\n}\n\n// Restore previous status\norder.status = order.previous_status || 'RELEASED';\ndelete order.previous_status;\ndelete order.hold_reason;\ndelete order.hold_at;\ndelete order.hold_by;\norder.released_hold_at = Date.now();\n\nglobal.set('outbound_dn_db', dnDB);\n\nmsg.topic = TOPIC;\nmsg.payload = {\n    version: '1.0',\n    topics: [{ path: TOPIC, type: 'state', value: dnDB }]\n};\n\nnode.warn('Order ' + action.dn_no + ' released from hold');\nreturn msg;",
        "outputs": 1,
        "timeout": "",
        "noerr": 0,
        "initialize": "",
        "finalize": "",
        "libs": [],
        "x": 1070,
        "y": 200,
        "wires": [["mqtt_out_dn_state"]]
    },
    {
        "id": "mqtt_in_review",
        "type": "mqtt in",
        "z": "flow_outbound",
        "g": "group_order_actions",
        "name": "Action: Review_DN",
        "topic": "Henkelv2/Shanghai/Logistics/Costing/Action/Review_DN",
        "qos": "0",
        "datatype": "json",
        "broker": "broker_emqx",
        "x": 860,
        "y": 260,
        "wires": [["func_review"]]
    },
    {
        "id": "func_review",
        "type": "function",
        "z": "flow_outbound",
        "g": "group_order_actions",
        "name": "Approve/Reject",
        "func": "const TOPIC = 'Henkelv2/Shanghai/Logistics/Costing/State/DN_Workflow_DB';\nlet action = msg.payload;\n\nlet dnDB = global.get('outbound_dn_db') || { items: [] };\nlet order = dnDB.items.find(o => o.dn_no === action.dn_no || o.id === action.dn_no);\n\nif (!order) {\n    node.warn('Review Error: Order not found');\n    return null;\n}\n\nif (action.action === 'APPROVE') {\n    order.status = 'RELEASED';\n    order.approved_by = action.operator || 'System';\n    order.approved_at = Date.now();\n} else if (action.action === 'REJECT') {\n    order.status = 'REJECTED';\n    order.reject_reason = action.reason || 'No reason';\n    order.rejected_by = action.operator || 'System';\n    order.rejected_at = Date.now();\n}\n\nglobal.set('outbound_dn_db', dnDB);\n\nmsg.topic = TOPIC;\nmsg.payload = {\n    version: '1.0',\n    topics: [{ path: TOPIC, type: 'state', value: dnDB }]\n};\n\nreturn msg;",
        "outputs": 1,
        "timeout": "",
        "noerr": 0,
        "initialize": "",
        "finalize": "",
        "libs": [],
        "x": 1080,
        "y": 260,
        "wires": [["mqtt_out_dn_state"]]
    },
    {
        "id": "mqtt_out_dn_state",
        "type": "mqtt out",
        "z": "flow_outbound",
        "g": "group_order_actions",
        "name": "Publish: DN State",
        "topic": "",
        "qos": "0",
        "retain": "true",
        "broker": "broker_emqx",
        "x": 1250,
        "y": 160,
        "wires": []
    },
    {
        "id": "group_wave_actions",
        "type": "group",
        "z": "flow_outbound",
        "name": "3. Wave Actions",
        "style": {
            "fill": "#60a5fa",
            "fill-opacity": "0.3",
            "label": true,
            "stroke": "#2563eb"
        },
        "nodes": [
            "mqtt_in_create_wave", "func_create_wave",
            "mqtt_in_add_wave", "func_add_wave",
            "mqtt_in_remove_wave", "func_remove_wave",
            "mqtt_in_release_wave", "func_release_wave",
            "mqtt_in_delete_wave", "func_delete_wave",
            "mqtt_out_wave_state", "mqtt_out_wave_dn"
        ],
        "x": 34,
        "y": 459,
        "w": 692,
        "h": 362
    },
    {
        "id": "mqtt_in_create_wave",
        "type": "mqtt in",
        "z": "flow_outbound",
        "g": "group_wave_actions",
        "name": "Action: Create_Wave",
        "topic": "Henkelv2/Shanghai/Logistics/Outbound/Action/Create_Wave",
        "qos": "0",
        "datatype": "json",
        "broker": "broker_emqx",
        "x": 150,
        "y": 520,
        "wires": [["func_create_wave"]]
    },
    {
        "id": "func_create_wave",
        "type": "function",
        "z": "flow_outbound",
        "g": "group_wave_actions",
        "name": "Create Empty Wave",
        "func": "const TOPIC = 'Henkelv2/Shanghai/Logistics/Outbound/State/Wave_List';\nlet action = msg.payload;\n\nlet waveDB = global.get('wave_db') || { items: [] };\n\n// Generate wave ID\nlet datePart = new Date().toISOString().slice(0, 10).replace(/-/g, '');\nlet key = 'wave_seq_' + datePart;\nlet seq = (global.get(key) || 0) + 1;\nglobal.set(key, seq);\n\nlet newWave = {\n    wave_id: action.wave_id || 'WAVE-' + datePart + '-' + String(seq).padStart(3, '0'),\n    status: 'PLANNED',\n    ship_date: action.ship_date || new Date().toISOString().split('T')[0],\n    carrier: action.carrier || null,\n    route: action.route || null,\n    pick_method: action.pick_method || 'BATCH',\n    delivery_ids: action.delivery_ids || [],\n    delivery_count: (action.delivery_ids || []).length,\n    line_count: 0,\n    picks_completed: 0,\n    picks_total: 0,\n    created_at: Date.now(),\n    created_by: action.operator || 'System'\n};\n\nwaveDB.items.unshift(newWave);\nglobal.set('wave_db', waveDB);\n\nmsg.topic = TOPIC;\nmsg.payload = {\n    version: '1.0',\n    topics: [{ path: TOPIC, type: 'state', value: waveDB }]\n};\n\nnode.warn('Created wave: ' + newWave.wave_id);\nreturn msg;",
        "outputs": 1,
        "timeout": "",
        "noerr": 0,
        "initialize": "",
        "finalize": "",
        "libs": [],
        "x": 370,
        "y": 520,
        "wires": [["mqtt_out_wave_state"]]
    },
    {
        "id": "mqtt_in_add_wave",
        "type": "mqtt in",
        "z": "flow_outbound",
        "g": "group_wave_actions",
        "name": "Action: Add_To_Wave",
        "topic": "Henkelv2/Shanghai/Logistics/Outbound/Action/Add_To_Wave",
        "qos": "0",
        "datatype": "json",
        "broker": "broker_emqx",
        "x": 150,
        "y": 580,
        "wires": [["func_add_wave"]]
    },
    {
        "id": "func_add_wave",
        "type": "function",
        "z": "flow_outbound",
        "g": "group_wave_actions",
        "name": "Add DN to Wave",
        "func": "const TOPIC_WAVE = 'Henkelv2/Shanghai/Logistics/Outbound/State/Wave_List';\nconst TOPIC_DN = 'Henkelv2/Shanghai/Logistics/Costing/State/DN_Workflow_DB';\nlet action = msg.payload;\n\nlet waveDB = global.get('wave_db') || { items: [] };\nlet dnDB = global.get('outbound_dn_db') || { items: [] };\n\n// Find wave\nlet wave = waveDB.items.find(w => w.wave_id === action.wave_id);\nif (!wave) {\n    node.warn('Add to Wave Error: Wave not found');\n    return null;\n}\n\nif (wave.status !== 'PLANNED') {\n    node.warn('Add to Wave Error: Wave not in PLANNED status');\n    return null;\n}\n\n// Find order\nlet order = dnDB.items.find(o => o.dn_no === action.dn_no || o.id === action.dn_no);\nif (!order) {\n    node.warn('Add to Wave Error: Order not found');\n    return null;\n}\n\n// Add order to wave\nif (!wave.delivery_ids.includes(order.dn_no)) {\n    wave.delivery_ids.push(order.dn_no);\n    wave.delivery_count = wave.delivery_ids.length;\n    wave.line_count += (order.lines || []).length;\n}\n\n// Update order\norder.wave_id = wave.wave_id;\norder.status = 'WAVE_ASSIGNED';\n\nglobal.set('wave_db', waveDB);\nglobal.set('outbound_dn_db', dnDB);\n\nlet msgWave = {\n    topic: TOPIC_WAVE,\n    payload: { version: '1.0', topics: [{ path: TOPIC_WAVE, type: 'state', value: waveDB }] }\n};\nlet msgDN = {\n    topic: TOPIC_DN,\n    payload: { version: '1.0', topics: [{ path: TOPIC_DN, type: 'state', value: dnDB }] }\n};\n\nnode.warn('Added ' + order.dn_no + ' to ' + wave.wave_id);\nreturn [[msgWave, msgDN]];",
        "outputs": 1,
        "timeout": "",
        "noerr": 0,
        "initialize": "",
        "finalize": "",
        "libs": [],
        "x": 360,
        "y": 580,
        "wires": [["mqtt_out_wave_state", "mqtt_out_wave_dn"]]
    },
    {
        "id": "mqtt_in_remove_wave",
        "type": "mqtt in",
        "z": "flow_outbound",
        "g": "group_wave_actions",
        "name": "Action: Remove_From_Wave",
        "topic": "Henkelv2/Shanghai/Logistics/Outbound/Action/Remove_From_Wave",
        "qos": "0",
        "datatype": "json",
        "broker": "broker_emqx",
        "x": 170,
        "y": 640,
        "wires": [["func_remove_wave"]]
    },
    {
        "id": "func_remove_wave",
        "type": "function",
        "z": "flow_outbound",
        "g": "group_wave_actions",
        "name": "Remove DN from Wave",
        "func": "const TOPIC_WAVE = 'Henkelv2/Shanghai/Logistics/Outbound/State/Wave_List';\nconst TOPIC_DN = 'Henkelv2/Shanghai/Logistics/Costing/State/DN_Workflow_DB';\nlet action = msg.payload;\n\nlet waveDB = global.get('wave_db') || { items: [] };\nlet dnDB = global.get('outbound_dn_db') || { items: [] };\n\nlet order = dnDB.items.find(o => o.dn_no === action.dn_no || o.id === action.dn_no);\nif (!order || !order.wave_id) {\n    node.warn('Remove from Wave Error: Order not found or not in wave');\n    return null;\n}\n\nlet wave = waveDB.items.find(w => w.wave_id === order.wave_id);\nif (wave) {\n    if (wave.status !== 'PLANNED') {\n        node.warn('Remove from Wave Error: Cannot modify wave in status ' + wave.status);\n        return null;\n    }\n    wave.delivery_ids = wave.delivery_ids.filter(id => id !== order.dn_no);\n    wave.delivery_count = wave.delivery_ids.length;\n    wave.line_count -= (order.lines || []).length;\n}\n\norder.wave_id = null;\norder.status = 'RELEASED';\n\nglobal.set('wave_db', waveDB);\nglobal.set('outbound_dn_db', dnDB);\n\nlet msgWave = {\n    topic: TOPIC_WAVE,\n    payload: { version: '1.0', topics: [{ path: TOPIC_WAVE, type: 'state', value: waveDB }] }\n};\nlet msgDN = {\n    topic: TOPIC_DN,\n    payload: { version: '1.0', topics: [{ path: TOPIC_DN, type: 'state', value: dnDB }] }\n};\n\nreturn [[msgWave, msgDN]];",
        "outputs": 1,
        "timeout": "",
        "noerr": 0,
        "initialize": "",
        "finalize": "",
        "libs": [],
        "x": 380,
        "y": 640,
        "wires": [["mqtt_out_wave_state", "mqtt_out_wave_dn"]]
    },
    {
        "id": "mqtt_in_release_wave",
        "type": "mqtt in",
        "z": "flow_outbound",
        "g": "group_wave_actions",
        "name": "Action: Release_Wave",
        "topic": "Henkelv2/Shanghai/Logistics/Outbound/Action/Release_Wave",
        "qos": "0",
        "datatype": "json",
        "broker": "broker_emqx",
        "x": 150,
        "y": 700,
        "wires": [["func_release_wave"]]
    },
    {
        "id": "func_release_wave",
        "type": "function",
        "z": "flow_outbound",
        "g": "group_wave_actions",
        "name": "Release Wave + Allocate",
        "func": "const TOPIC_WAVE = 'Henkelv2/Shanghai/Logistics/Outbound/State/Wave_List';\nconst TOPIC_DN = 'Henkelv2/Shanghai/Logistics/Costing/State/DN_Workflow_DB';\nconst TOPIC_TASKS = 'Henkelv2/Shanghai/Logistics/Outbound/State/Picking_Queue';\nlet action = msg.payload;\n\nlet waveDB = global.get('wave_db') || { items: [] };\nlet dnDB = global.get('outbound_dn_db') || { items: [] };\nlet taskDB = global.get('outbound_task_db') || { items: [] };\n\nlet wave = waveDB.items.find(w => w.wave_id === action.wave_id);\nif (!wave) {\n    node.warn('Release Wave Error: Wave not found ' + action.wave_id);\n    return null;\n}\n\nif (wave.status !== 'PLANNED') {\n    node.warn('Release Wave Error: Wave not in PLANNED status');\n    return null;\n}\n\nif (wave.delivery_ids.length === 0) {\n    node.warn('Release Wave Error: Wave has no orders');\n    return null;\n}\n\n// Update wave status\nwave.status = 'RELEASED';\nwave.released_at = Date.now();\nwave.released_by = action.operator || 'System';\n\nlet totalPicks = 0;\nconst locations = ['A-01-01', 'A-02-03', 'B-01-02', 'B-03-01', 'C-02-04'];\n\n// Process each delivery in the wave\nwave.delivery_ids.forEach(dnId => {\n    let order = dnDB.items.find(o => o.dn_no === dnId);\n    if (!order) return;\n    \n    order.status = 'ALLOCATED';\n    order.allocated_at = Date.now();\n    \n    // Create pick tasks for each line\n    (order.lines || []).forEach((line, idx) => {\n        let newTask = {\n            task_id: 'PICK-' + Date.now() + '-' + Math.floor(Math.random() * 1000),\n            wave_id: wave.wave_id,\n            dn_no: order.dn_no,\n            material_code: line.code,\n            material_name: line.code,\n            batch: 'B2026' + String(Math.floor(Math.random() * 1000)).padStart(3, '0'),\n            qty: line.qty,\n            from_location: locations[Math.floor(Math.random() * locations.length)],\n            to_location: 'STAGE-01',\n            status: 'PENDING',\n            priority: order.priority || 'NORMAL',\n            created_at: Date.now()\n        };\n        taskDB.items.unshift(newTask);\n        totalPicks++;\n        \n        line.qty_allocated = line.qty;\n    });\n});\n\nwave.picks_total = totalPicks;\nwave.status = 'IN_PROGRESS';\n\nglobal.set('wave_db', waveDB);\nglobal.set('outbound_dn_db', dnDB);\nglobal.set('outbound_task_db', taskDB);\n\nlet msgWave = {\n    topic: TOPIC_WAVE,\n    payload: { version: '1.0', topics: [{ path: TOPIC_WAVE, type: 'state', value: waveDB }] }\n};\nlet msgDN = {\n    topic: TOPIC_DN,\n    payload: { version: '1.0', topics: [{ path: TOPIC_DN, type: 'state', value: dnDB }] }\n};\nlet msgTasks = {\n    topic: TOPIC_TASKS,\n    payload: { version: '1.0', topics: [{ path: TOPIC_TASKS, type: 'state', value: { tasks: taskDB.items } }] }\n};\n\nnode.warn('Released wave ' + wave.wave_id + ' with ' + totalPicks + ' pick tasks');\nreturn [[msgWave, msgDN, msgTasks]];",
        "outputs": 1,
        "timeout": "",
        "noerr": 0,
        "initialize": "",
        "finalize": "",
        "libs": [],
        "x": 380,
        "y": 700,
        "wires": [["mqtt_out_wave_state", "mqtt_out_wave_dn"]]
    },
    {
        "id": "mqtt_in_delete_wave",
        "type": "mqtt in",
        "z": "flow_outbound",
        "g": "group_wave_actions",
        "name": "Action: Delete_Wave",
        "topic": "Henkelv2/Shanghai/Logistics/Outbound/Action/Delete_Wave",
        "qos": "0",
        "datatype": "json",
        "broker": "broker_emqx",
        "x": 150,
        "y": 760,
        "wires": [["func_delete_wave"]]
    },
    {
        "id": "func_delete_wave",
        "type": "function",
        "z": "flow_outbound",
        "g": "group_wave_actions",
        "name": "Delete Wave",
        "func": "const TOPIC_WAVE = 'Henkelv2/Shanghai/Logistics/Outbound/State/Wave_List';\nconst TOPIC_DN = 'Henkelv2/Shanghai/Logistics/Costing/State/DN_Workflow_DB';\nlet action = msg.payload;\n\nlet waveDB = global.get('wave_db') || { items: [] };\nlet dnDB = global.get('outbound_dn_db') || { items: [] };\n\nlet wave = waveDB.items.find(w => w.wave_id === action.wave_id);\nif (!wave) {\n    node.warn('Delete Wave: Wave not found');\n    return null;\n}\n\nif (wave.status !== 'PLANNED' && wave.status !== 'RELEASED') {\n    node.warn('Delete Wave: Cannot delete wave in status ' + wave.status);\n    return null;\n}\n\n// Unassign orders from this wave\n(wave.delivery_ids || []).forEach(dnId => {\n    let order = dnDB.items.find(o => o.dn_no === dnId);\n    if (order) {\n        order.wave_id = null;\n        order.status = 'RELEASED';\n    }\n});\n\n// Remove wave\nwaveDB.items = waveDB.items.filter(w => w.wave_id !== action.wave_id);\n\nglobal.set('wave_db', waveDB);\nglobal.set('outbound_dn_db', dnDB);\n\nlet msgWave = {\n    topic: TOPIC_WAVE,\n    payload: { version: '1.0', topics: [{ path: TOPIC_WAVE, type: 'state', value: waveDB }] }\n};\nlet msgDN = {\n    topic: TOPIC_DN,\n    payload: { version: '1.0', topics: [{ path: TOPIC_DN, type: 'state', value: dnDB }] }\n};\n\nnode.warn('Deleted wave ' + action.wave_id);\nreturn [[msgWave, msgDN]];",
        "outputs": 1,
        "timeout": "",
        "noerr": 0,
        "initialize": "",
        "finalize": "",
        "libs": [],
        "x": 350,
        "y": 760,
        "wires": [["mqtt_out_wave_state", "mqtt_out_wave_dn"]]
    },
    {
        "id": "mqtt_out_wave_state",
        "type": "mqtt out",
        "z": "flow_outbound",
        "g": "group_wave_actions",
        "name": "Publish: Wave State",
        "topic": "",
        "qos": "0",
        "retain": "true",
        "broker": "broker_emqx",
        "x": 600,
        "y": 580,
        "wires": []
    },
    {
        "id": "mqtt_out_wave_dn",
        "type": "mqtt out",
        "z": "flow_outbound",
        "g": "group_wave_actions",
        "name": "Publish: DN State",
        "topic": "",
        "qos": "0",
        "retain": "true",
        "broker": "broker_emqx",
        "x": 600,
        "y": 700,
        "wires": []
    },
    {
        "id": "group_execution",
        "type": "group",
        "z": "flow_outbound",
        "name": "4. Execution Actions",
        "style": {
            "fill": "#fb923c",
            "fill-opacity": "0.3",
            "label": true,
            "stroke": "#ea580c"
        },
        "nodes": [
            "mqtt_in_confirm_pick", "func_confirm_pick",
            "mqtt_in_short_pick", "func_short_pick",
            "mqtt_in_confirm_stage", "func_confirm_stage",
            "mqtt_in_confirm_load", "func_confirm_load",
            "mqtt_out_exec_state"
        ],
        "x": 754,
        "y": 339,
        "w": 572,
        "h": 302
    },
    {
        "id": "mqtt_in_confirm_pick",
        "type": "mqtt in",
        "z": "flow_outbound",
        "g": "group_execution",
        "name": "Action: Confirm_Pick",
        "topic": "Henkelv2/Shanghai/Logistics/Outbound/Action/Confirm_Pick",
        "qos": "0",
        "datatype": "json",
        "broker": "broker_emqx",
        "x": 870,
        "y": 400,
        "wires": [["func_confirm_pick"]]
    },
    {
        "id": "func_confirm_pick",
        "type": "function",
        "z": "flow_outbound",
        "g": "group_execution",
        "name": "Confirm Pick",
        "func": "const TOPIC = 'Henkelv2/Shanghai/Logistics/Outbound/State/Picking_Queue';\nlet action = msg.payload;\n\nlet taskDB = global.get('outbound_task_db') || { items: [] };\nlet waveDB = global.get('wave_db') || { items: [] };\n\nlet task = taskDB.items.find(t => t.task_id === action.task_id);\nif (!task) {\n    node.warn('Confirm Pick: Task not found');\n    return null;\n}\n\ntask.status = 'COMPLETED';\ntask.completed_at = Date.now();\ntask.picked_qty = action.picked_qty || action.qty_picked || task.qty;\ntask.operator = action.operator || 'System';\n\n// Update wave progress\nlet wave = waveDB.items.find(w => w.wave_id === task.wave_id);\nif (wave) {\n    wave.picks_completed = (wave.picks_completed || 0) + 1;\n    if (wave.picks_completed >= wave.picks_total) {\n        wave.status = 'COMPLETED';\n        wave.completed_at = Date.now();\n    }\n    global.set('wave_db', waveDB);\n}\n\nglobal.set('outbound_task_db', taskDB);\n\nmsg.topic = TOPIC;\nmsg.payload = {\n    version: '1.0',\n    topics: [{ path: TOPIC, type: 'state', value: { tasks: taskDB.items } }]\n};\n\nreturn msg;",
        "outputs": 1,
        "timeout": "",
        "noerr": 0,
        "initialize": "",
        "finalize": "",
        "libs": [],
        "x": 1070,
        "y": 400,
        "wires": [["mqtt_out_exec_state"]]
    },
    {
        "id": "mqtt_in_short_pick",
        "type": "mqtt in",
        "z": "flow_outbound",
        "g": "group_execution",
        "name": "Action: Report_Short_Pick",
        "topic": "Henkelv2/Shanghai/Logistics/Outbound/Action/Report_Short_Pick",
        "qos": "0",
        "datatype": "json",
        "broker": "broker_emqx",
        "x": 890,
        "y": 460,
        "wires": [["func_short_pick"]]
    },
    {
        "id": "func_short_pick",
        "type": "function",
        "z": "flow_outbound",
        "g": "group_execution",
        "name": "Report Short Pick",
        "func": "const TOPIC = 'Henkelv2/Shanghai/Logistics/Outbound/State/Picking_Queue';\nlet action = msg.payload;\n\nlet taskDB = global.get('outbound_task_db') || { items: [] };\n\nlet task = taskDB.items.find(t => t.task_id === action.task_id);\nif (!task) {\n    node.warn('Report Short Pick: Task not found');\n    return null;\n}\n\ntask.status = 'SHORT_PICK';\ntask.short_reason = action.reason || 'UNKNOWN';\ntask.actual_qty = action.actual_qty || 0;\ntask.expected_qty = action.expected_qty || task.qty;\ntask.operator = action.operator || 'System';\ntask.updated_at = Date.now();\n\nglobal.set('outbound_task_db', taskDB);\n\nmsg.topic = TOPIC;\nmsg.payload = {\n    version: '1.0',\n    topics: [{ path: TOPIC, type: 'state', value: { tasks: taskDB.items } }]\n};\n\nreturn msg;",
        "outputs": 1,
        "timeout": "",
        "noerr": 0,
        "initialize": "",
        "finalize": "",
        "libs": [],
        "x": 1090,
        "y": 460,
        "wires": [["mqtt_out_exec_state"]]
    },
    {
        "id": "mqtt_in_confirm_stage",
        "type": "mqtt in",
        "z": "flow_outbound",
        "g": "group_execution",
        "name": "Action: Confirm_Stage",
        "topic": "Henkelv2/Shanghai/Logistics/Outbound/Action/Confirm_Stage",
        "qos": "0",
        "datatype": "json",
        "broker": "broker_emqx",
        "x": 880,
        "y": 520,
        "wires": [["func_confirm_stage"]]
    },
    {
        "id": "func_confirm_stage",
        "type": "function",
        "z": "flow_outbound",
        "g": "group_execution",
        "name": "Confirm Stage",
        "func": "const TOPIC = 'Henkelv2/Shanghai/Logistics/Outbound/State/Staging_Area';\nlet action = msg.payload;\n\nlet staging = global.get('staging_areas') || { areas: [] };\nif (!staging.areas || !Array.isArray(staging.areas)) {\n    staging.areas = [\n        { area_id: 'STAGE-01', items: [] },\n        { area_id: 'STAGE-02', items: [] },\n        { area_id: 'STAGE-03', items: [] }\n    ];\n}\n\nlet area = staging.areas.find(a => a.area_id === action.area_id);\nif (!area) {\n    area = { area_id: action.area_id, items: [] };\n    staging.areas.push(area);\n}\n\narea.items = area.items.filter(i => i.dn_no !== action.dn_no);\narea.items.push({\n    dn_no: action.dn_no,\n    staged_at: Date.now(),\n    operator: action.operator || 'System'\n});\narea.used = area.items.length;\n\nglobal.set('staging_areas', staging);\n\nmsg.topic = TOPIC;\nmsg.payload = {\n    version: '1.0',\n    topics: [{ path: TOPIC, type: 'state', value: staging }]\n};\n\nreturn msg;",
        "outputs": 1,
        "timeout": "",
        "noerr": 0,
        "initialize": "",
        "finalize": "",
        "libs": [],
        "x": 1080,
        "y": 520,
        "wires": [["mqtt_out_exec_state"]]
    },
    {
        "id": "mqtt_in_confirm_load",
        "type": "mqtt in",
        "z": "flow_outbound",
        "g": "group_execution",
        "name": "Action: Confirm_Load",
        "topic": "Henkelv2/Shanghai/Logistics/Outbound/Action/Confirm_Load",
        "qos": "0",
        "datatype": "json",
        "broker": "broker_emqx",
        "x": 880,
        "y": 580,
        "wires": [["func_confirm_load"]]
    },
    {
        "id": "func_confirm_load",
        "type": "function",
        "z": "flow_outbound",
        "g": "group_execution",
        "name": "Confirm Load",
        "func": "const TOPIC_DOCKS = 'Henkelv2/Shanghai/Logistics/Outbound/State/Loading_Docks';\nconst TOPIC_SHIP = 'Henkelv2/Shanghai/Logistics/Outbound/State/Shipment_List';\nlet action = msg.payload;\n\nlet shipmentList = global.get('shipment_list') || { items: [] };\nlet docks = global.get('loading_docks') || { docks: [] };\n\nlet ship = shipmentList.items.find(s => s.shipment_id === action.shipment_id || s.dn_id === action.shipment_id);\nif (ship) {\n    ship.status = 'LOADED';\n    ship.loaded_at = Date.now();\n    ship.dock_id = action.dock_id;\n}\n\nlet dock = docks.docks.find(d => d.dock_id === action.dock_id);\nif (dock) {\n    dock.status = 'AVAILABLE';\n    dock.shipment_id = null;\n}\n\nglobal.set('shipment_list', shipmentList);\nglobal.set('loading_docks', docks);\n\nlet msgDocks = {\n    topic: TOPIC_DOCKS,\n    payload: { version: '1.0', topics: [{ path: TOPIC_DOCKS, type: 'state', value: docks }] }\n};\nlet msgShip = {\n    topic: TOPIC_SHIP,\n    payload: { version: '1.0', topics: [{ path: TOPIC_SHIP, type: 'state', value: shipmentList }] }\n};\n\nreturn [[msgDocks, msgShip]];",
        "outputs": 1,
        "timeout": "",
        "noerr": 0,
        "initialize": "",
        "finalize": "",
        "libs": [],
        "x": 1070,
        "y": 580,
        "wires": [["mqtt_out_exec_state"]]
    },
    {
        "id": "mqtt_out_exec_state",
        "type": "mqtt out",
        "z": "flow_outbound",
        "g": "group_execution",
        "name": "Publish State",
        "topic": "",
        "qos": "0",
        "retain": "true",
        "broker": "broker_emqx",
        "x": 1250,
        "y": 480,
        "wires": []
    },
    {
        "id": "group_dispatch",
        "type": "group",
        "z": "flow_outbound",
        "name": "5. Dispatch Actions",
        "style": {
            "fill": "#c084fc",
            "fill-opacity": "0.3",
            "label": true,
            "stroke": "#9333ea"
        },
        "nodes": [
            "mqtt_in_create_shipment", "func_create_shipment",
            "mqtt_in_outbound_pick", "func_outbound_pick",
            "mqtt_in_confirm_pack", "func_confirm_pack",
            "mqtt_in_confirm_ship", "func_confirm_ship",
            "mqtt_out_dispatch_state"
        ],
        "x": 34,
        "y": 839,
        "w": 572,
        "h": 302
    },
    {
        "id": "mqtt_in_create_shipment",
        "type": "mqtt in",
        "z": "flow_outbound",
        "g": "group_dispatch",
        "name": "Action: Create_Shipment",
        "topic": "Henkelv2/Shanghai/Logistics/Outbound/Action/Create_Shipment",
        "qos": "0",
        "datatype": "json",
        "broker": "broker_emqx",
        "x": 160,
        "y": 900,
        "wires": [["func_create_shipment"]]
    },
    {
        "id": "func_create_shipment",
        "type": "function",
        "z": "flow_outbound",
        "g": "group_dispatch",
        "name": "Create Shipment",
        "func": "const TOPIC = 'Henkelv2/Shanghai/Logistics/Outbound/State/Shipment_List';\nlet action = msg.payload;\n\nlet shipmentList = global.get('shipment_list') || { items: [] };\n\nlet shipment_id = 'SHP-' + Date.now();\nlet newShipment = {\n    shipment_id: shipment_id,\n    dn_id: shipment_id,\n    customer: action.customer || 'Unknown',\n    destination: action.destination || '',\n    items: action.items || [],\n    status: 'READY_TO_PICK',\n    created_at: Date.now(),\n    created_by: action.created_by || 'System'\n};\n\nshipmentList.items.unshift(newShipment);\nif (shipmentList.items.length > 50) shipmentList.items = shipmentList.items.slice(0, 50);\n\nglobal.set('shipment_list', shipmentList);\n\nmsg.topic = TOPIC;\nmsg.payload = {\n    version: '1.0',\n    topics: [{ path: TOPIC, type: 'state', value: shipmentList }]\n};\n\nnode.warn('Created shipment: ' + shipment_id);\nreturn msg;",
        "outputs": 1,
        "timeout": "",
        "noerr": 0,
        "initialize": "",
        "finalize": "",
        "libs": [],
        "x": 370,
        "y": 900,
        "wires": [["mqtt_out_dispatch_state"]]
    },
    {
        "id": "mqtt_in_outbound_pick",
        "type": "mqtt in",
        "z": "flow_outbound",
        "g": "group_dispatch",
        "name": "Action: Confirm_Outbound_Pick",
        "topic": "Henkelv2/Shanghai/Logistics/Outbound/Action/Confirm_Outbound_Pick",
        "qos": "0",
        "datatype": "json",
        "broker": "broker_emqx",
        "x": 180,
        "y": 960,
        "wires": [["func_outbound_pick"]]
    },
    {
        "id": "func_outbound_pick",
        "type": "function",
        "z": "flow_outbound",
        "g": "group_dispatch",
        "name": "Confirm Outbound Pick",
        "func": "const TOPIC = 'Henkelv2/Shanghai/Logistics/Outbound/State/Shipment_List';\nlet action = msg.payload;\n\nlet shipmentList = global.get('shipment_list') || { items: [] };\n\nlet ship = shipmentList.items.find(s => s.dn_id === action.dn_id || s.shipment_id === action.dn_id);\nif (!ship) {\n    node.warn('Confirm Outbound Pick: Shipment not found');\n    return null;\n}\n\nship.status = 'PICKED';\nship.picked_at = Date.now();\nship.picked_by = action.operator || 'System';\n\nglobal.set('shipment_list', shipmentList);\n\nmsg.topic = TOPIC;\nmsg.payload = {\n    version: '1.0',\n    topics: [{ path: TOPIC, type: 'state', value: shipmentList }]\n};\n\nreturn msg;",
        "outputs": 1,
        "timeout": "",
        "noerr": 0,
        "initialize": "",
        "finalize": "",
        "libs": [],
        "x": 390,
        "y": 960,
        "wires": [["mqtt_out_dispatch_state"]]
    },
    {
        "id": "mqtt_in_confirm_pack",
        "type": "mqtt in",
        "z": "flow_outbound",
        "g": "group_dispatch",
        "name": "Action: Confirm_Pack",
        "topic": "Henkelv2/Shanghai/Logistics/Outbound/Action/Confirm_Pack",
        "qos": "0",
        "datatype": "json",
        "broker": "broker_emqx",
        "x": 150,
        "y": 1020,
        "wires": [["func_confirm_pack"]]
    },
    {
        "id": "func_confirm_pack",
        "type": "function",
        "z": "flow_outbound",
        "g": "group_dispatch",
        "name": "Confirm Pack",
        "func": "const TOPIC = 'Henkelv2/Shanghai/Logistics/Outbound/State/Shipment_List';\nlet action = msg.payload;\n\nlet shipmentList = global.get('shipment_list') || { items: [] };\n\nlet ship = shipmentList.items.find(s => s.dn_id === action.dn_id || s.shipment_id === action.dn_id);\nif (!ship) {\n    node.warn('Confirm Pack: Shipment not found');\n    return null;\n}\n\nship.status = 'READY_TO_SHIP';\nship.packed_at = Date.now();\nship.packer = action.packer || 'System';\n\nglobal.set('shipment_list', shipmentList);\n\nmsg.topic = TOPIC;\nmsg.payload = {\n    version: '1.0',\n    topics: [{ path: TOPIC, type: 'state', value: shipmentList }]\n};\n\nreturn msg;",
        "outputs": 1,
        "timeout": "",
        "noerr": 0,
        "initialize": "",
        "finalize": "",
        "libs": [],
        "x": 360,
        "y": 1020,
        "wires": [["mqtt_out_dispatch_state"]]
    },
    {
        "id": "mqtt_in_confirm_ship",
        "type": "mqtt in",
        "z": "flow_outbound",
        "g": "group_dispatch",
        "name": "Action: Confirm_Ship",
        "topic": "Henkelv2/Shanghai/Logistics/Outbound/Action/Confirm_Ship",
        "qos": "0",
        "datatype": "json",
        "broker": "broker_emqx",
        "x": 150,
        "y": 1080,
        "wires": [["func_confirm_ship"]]
    },
    {
        "id": "func_confirm_ship",
        "type": "function",
        "z": "flow_outbound",
        "g": "group_dispatch",
        "name": "Confirm Ship",
        "func": "const TOPIC = 'Henkelv2/Shanghai/Logistics/Outbound/State/Shipment_List';\nlet action = msg.payload;\n\nlet shipmentList = global.get('shipment_list') || { items: [] };\n\nlet ship = shipmentList.items.find(s => s.dn_id === action.dn_id || s.shipment_id === action.dn_id);\nif (!ship) {\n    node.warn('Confirm Ship: Shipment not found');\n    return null;\n}\n\nship.status = 'SHIPPED';\nship.shipped_at = Date.now();\nship.carrier_info = action.carrier_info || {};\n\nglobal.set('shipment_list', shipmentList);\n\nmsg.topic = TOPIC;\nmsg.payload = {\n    version: '1.0',\n    topics: [{ path: TOPIC, type: 'state', value: shipmentList }]\n};\n\nnode.warn('Shipment ' + ship.shipment_id + ' shipped!');\nreturn msg;",
        "outputs": 1,
        "timeout": "",
        "noerr": 0,
        "initialize": "",
        "finalize": "",
        "libs": [],
        "x": 360,
        "y": 1080,
        "wires": [["mqtt_out_dispatch_state"]]
    },
    {
        "id": "mqtt_out_dispatch_state",
        "type": "mqtt out",
        "z": "flow_outbound",
        "g": "group_dispatch",
        "name": "Publish State",
        "topic": "",
        "qos": "0",
        "retain": "true",
        "broker": "broker_emqx",
        "x": 530,
        "y": 980,
        "wires": []
    }
]
